<page>
    <title>Carles Buïgas i Sans</title>
    <ns>0</ns>
    <id>243315</id>
    <revision>
      <id>13689165</id>
      <parentid>13517431</parentid>
      <timestamp>2014-06-26T00:55:27Z</timestamp>
      <contributor>
        <username>PereBot</username>
        <id>118448</id>
      </contributor>
      <minor></minor>
      <comment>Robot inserta {{Autoritat}}</comment>
      <text>'''Carles Buïgas i Sans''' ([[Barcelona]], [[18 de gener]] de [[1898]] - [[Cerdanyola del Vallès]], [[27 d'agost]] de [[1979]]) va ser un [[arquitectura|arquitecte]], enginyer i luminotècnic [[Catalunya|català]] conegut per haver dissenyat la il·luminació del [[Palau Nacional (Barcelona)]] i del recinte de l'[[Exposició Internacional de Barcelona de 1929]], així com la [[Font Màgica de Montjuïc]]. En els anys següents va
projectar la il·luminació i les fonts monumentals que van presidir el recinte de l'Exposició. Posteriorment va treballar en el projecte de fonts per a ciutats de l'Estat espanyol i l'estranger.ref name=AFB2007{{Cita Barcelona fotografiada|pàgina=194}}/ref

== Biografia ==
Fill de [[Gaietà Buïgas i Monravà|Gaietà Buïgas]], fou criat al si d'una família acomodada a Barcelona. Als 7 anys va marxar amb la seva familia a [[Montevideo]] ([[Uruguai]]) per motius de feina del seu pare. La familia va tornar a Barcelona el 1910 degut a la crisi econòmic existent a l'Uruguai. El [[1916]] va ingressar a l'[[escola d'Enginyers industrials de Barcelona]], però no va finalitzar els estudis a causa del fet que va començar a treballar com a ajudant del futur projecte de l'Exposició d'Indústries Elèctriques de Barcelona. Més endavant es titularia a l'École de Génie Civil de [[París]].

El [[1922]] va començar a dissenyar el seu primer projecte de fonts i salts d'aigua lluminosos. Les seves primeres obres van ser al [[Palau Reial de Pedralbes]]. [[Eugeni d'Ors]] definiria el seu treball com un nou estil d'art, l'art de l'''aiguallum''.

El [[1926]] va idear el [[Telefèric del Port]] amb la idea de posar-la en marxa per l'[[Exposició Internacional de 1929|Exposició Universal de 1929]], però no es va fer realitat fins al [[1931]] per falta de fons.

Més endavant va realitzar el projecte que el faria famós, la [[font màgica de Montjuïc]], creada amb motiu de l'[[Exposició Internacional de 1929]] a [[Barcelona]]. També fou autor dels brolladors d'aigua de l'avinguda de la Reina Maria Cristina. Un cop finalitzada l'exposició, va començar altres projectes, com ara la ''Nau Lluminosa'' (o Vaixell Lluminós), declarada en el seu moment ''projecte d'interès nacional''. 

Amb la [[Guerra Civil espanyola|Guerra Civil]], va marxar a [[París]], on va residir fins al 1942. Durant aquests anys va guanyar renom internacional i va realitzar projectes a París, [[Lieja]], [[Nova York]], [[Lisboa]], [[Roma]], [[Santo Domingo]], [[Madrid]], [[Granada (Andalusia)|Granada]], [[València]]...

Degut a la crisis existent un cop finalitzada la [[Segona Guerra Mundial]], molts dels projectes encarregats a Buïgas van ser aturats o anul·lats. 

Va passar els últims anys de la seva vida a [[Cerdanyola del Vallès]], on va morir i és enterrat.

== Obra ==
A més de la seva tasca com a enginyer, Buïgas va col·laborar en diverses ocasions com a columnista de [[La Vanguardia]] i d'altres publicacions, i va publicar diferents llibres.

=== [[Barcelona]] ===
{| bgcolor=#f7f8ff cellpadding=4 cellspacing=0 border=1 style=font-size: 95%; border: #cccccc solid 1px; border-collapse: collapse;
!width=5% style=background:#ffce5d; |Any
!width=15% style=background:#ffce5d; |Nom
!width=15% style=background:#ffce5d; |Ubicació
!width=45% style=background:#ffce5d; |Descripció
!width=5% style=background:#ffce5d; |Estat
!width=15% style=background:#ffce5d; |Foto
|-----
|-
|[[1929]]
|[[Font màgica de Montjuïc]]{{sfn|Tatjer |1998|p=108}}
|Montjuïc
|Gran font llunminosa i canviant que forma part del conjunt de fonts que s'estenen des del Palau Nacional fins a la plaça d'Espanya realitzades per Buïgas per a l'Exposició Internacional del 1929.
|Bo, restaurada el 1955 i 1992.
|[[Fitxer:Font Màgica de Montjuïc.jpg|140px|Font Màgica de Montjuïc]]
|-
|[[1931]]
|[[Telefèric del Port]]{{sfn|Silva |1981|p=92}}
|Montjuïc
|Transbordador aeri que uneix [[la Barceloneta]] i el port de Barcelona amb [[Montjuïc (Barcelona)|Montjuïc]].
|Bo, reobert el 1963.
|[[Fitxer:050529 Barcelona 083.jpg|140px|Telefèric del port]]
|-
|[[1964]]
|Il·luminació de la Sagrada Família{{sfn|Tatjer |1998|p=110}}
|[[Temple Expiatori de la Sagrada Família]]
|Il·luminació artística de la Façana del Naixement del temple.
|?
|[[Fitxer:Barcelona Iglesia Sagrada Familia 02.jpg|140px|Sagrada Família]]
|-
|[[1968]]
|Petita font lluminosa i canviant{{sfn|Tatjer |1998|p=107}}
|[[Parc d'atraccions de Montjuïc]] actualment [[Jardins de Joan Brossa]]
|Font circular.
|?
|
|-
|[[1969]]
|Font dels [[Jardins del Mirador de l'Alcalde]]ref name=ajAjuntament de Barcelona, [http://w110.bcn.cat/portal/site/MediAmbient/menuitem.0d4d06202ea41e13e9c5e9c5a2ef8a0c/?vgnextoid=caeb57f113b6a210VgnVCM10000074fea8c0RCRDvgnextchannel=6de179583ad1a210VgnVCM10000074fea8c0RCRDlang=ca_ES Mirador de l'Alcalde]/ref
| [[Jardins del Mirador de l'Alcalde]], Montjuïc
|Font ornamental.
|Bo, reobert el 2009
|[[Fitxer:Jardins del Mirador de l'Alcalde (Montjuïc - Barcelona) 08.JPG|140px|Font dels Jardins del Mirador de l'Alcalde]]
|-
|}

=== [[Granada (Andalusia)|Granada]] ===
{| bgcolor=#f7f8ff cellpadding=4 cellspacing=0 border=1 style=font-size: 95%; border: #cccccc solid 1px; border-collapse: collapse;
!width=5% style=background:#ffce5d; |Any
!width=15% style=background:#ffce5d; |Nom
!width=15% style=background:#ffce5d; |Ubicació
!width=45% style=background:#ffce5d; |Descripció
!width=5% style=background:#ffce5d; |Estat
!width=15% style=background:#ffce5d; |Foto
|-----
|-
|[[1960]]
|Font lluminosa lineal{{sfn|Tatjer |1998|p=107}}
|Explanada del Triunfo
|Font de 75 metres de llarg que envolta el monument al Triomf de la Verge. 
|?
| [[Fitxer:Fuentetriunfo.jpg|140px|Fuente del Triunfo]]
|-
|}
=== [[Madrid]] ===
{| bgcolor=#f7f8ff cellpadding=4 cellspacing=0 border=1 style=font-size: 95%; border: #cccccc solid 1px; border-collapse: collapse;
!width=5% style=background:#ffce5d; |Any
!width=15% style=background:#ffce5d; |Nom
!width=15% style=background:#ffce5d; |Ubicació
!width=45% style=background:#ffce5d; |Descripció
!width=5% style=background:#ffce5d; |Estat
!width=15% style=background:#ffce5d; |Foto
|-----
|-
|[[1969]]
|Restaurant elevat{{sfn|Silva |1981|p=93}}
|Parc d'Atraccions de la Casa de Campo
|Conjunt de fonts, cascades i sortidors lluminosos i restaurant elevat sobre plataforma de la que descendeix una cascada d'aigua il·luminada.
|?
|
|-
|}
=== [[Sant Adrià del Besòs]] ===
{| bgcolor=#f7f8ff cellpadding=4 cellspacing=0 border=1 style=font-size: 95%; border: #cccccc solid 1px; border-collapse: collapse;
!width=5% style=background:#ffce5d; |Any
!width=15% style=background:#ffce5d; |Nom
!width=15% style=background:#ffce5d; |Ubicació
!width=45% style=background:#ffce5d; |Descripció
!width=5% style=background:#ffce5d; |Estat
!width=15% style=background:#ffce5d; |Foto
|-----
|-
|[[1971]]
|Font lluminosa canviant{{sfn|Tatjer |1998|p=107}}
|?
|Petita font circular. 
|?
|
|-
|}
=== [[València]] ===
{| bgcolor=#f7f8ff cellpadding=4 cellspacing=0 border=1 style=font-size: 95%; border: #cccccc solid 1px; border-collapse: collapse;
!width=5% style=background:#ffce5d; |Any
!width=15% style=background:#ffce5d; |Nom
!width=15% style=background:#ffce5d; |Ubicació
!width=45% style=background:#ffce5d; |Descripció
!width=5% style=background:#ffce5d; |Estat
!width=15% style=background:#ffce5d; |Foto
|-----
|-
|[[1963]]
|Font lluminosa canviant{{sfn|Silva |1981|p=92}}
|Plaça de l'Ajuntament
|Font circular. 
|Correcte
| [[Fitxer:Plaza del Ayuntamiento - 5. January 2006 - 2.jpg|140px|Plaça de l'Ajuntament de València]]
|-
|}

=== [[Santo Domingo]], [[República Dominicana]] ===
{| bgcolor=#f7f8ff cellpadding=4 cellspacing=0 border=1 style=font-size: 95%; border: #cccccc solid 1px; border-collapse: collapse;
!width=5% style=background:#ffce5d; |Any
!width=15% style=background:#ffce5d; |Nom
!width=15% style=background:#ffce5d; |Ubicació
!width=45% style=background:#ffce5d; |Descripció
!width=5% style=background:#ffce5d; |Estat
!width=15% style=background:#ffce5d; |Foto
|-----
|-
|[[1955]]
|Teatro Agua y Luz
|Barri del Centro de los Héroes de Maimón, Constanza y Estero Hondo, [[Santo Domingo]]
|Amfiteatre d'estil racionalista amb instal·lacions de font lluminosa i canviant que feia de rerefons a obres escèniques. Obra realitzada per Buïgas per a la Feria de la Paz y Confraternidad del Mundo Libre del [[1955]]-[[1956|56]]. Declarat patrimoni d'interès nacional el [[1988]].
|Actualment ([[2014]]) en estat semi-ruïnós i en perill de ser enderrocat per fer lloc per a un aparcament o altre projecte.ref[https://www.youtube.com/watch?v=Jc2D-yx2eTs Reportatge sobre el teatre] a Cachita.com/refref[http://www.conectate.com.do/articulo/teatro-agua-y-luz-santo-domingo-republica-dominicana-fotos-turismo/ Teatro Agua y Luz de Santo Domingo], Bethania Ortega, gener del 2013./ref
|Es poden veure imatges [https://www.youtube.com/watch?v=Jc2D-yx2eTs en aquest vídeo], i a [http://imagenesdenuestrahistoria.com/2013/08/30/teatro-agua-y-luz/ Imágenes de nuestra historia].
|-
|}

=== Altres obres rellevants ===
* Fonts de l'[[Aeroport del Prat]]
* Teatre Integral de la Llum (projecte)
* Vaixell Lluminós (projecte)

=== Llibres Publicats ===
* [[1940]] - {{ref-llibre|títol=Bajo las constelaciones: (Viajes de Gil del Mar)|url=http://books.google.com/books?id=hMj7OwAACAAJ|any=1940|editorial=Bruguera|llengua=castellà}}
* [[1946]] - {{ref-llibre|títol=El Hombre entre enigmas y prodigios|url=http://books.google.com/books?id=PoE-ygAACAAJ|any=1946|editorial=Hymsa|llengua=castellà}}
* [[1960]] - {{ref-llibre|cognom=|nom=|títol=La nave luminosa|url=http://books.google.com/books?id=kY0KAQAAMAAJ|any=1960|editorial=Editorial Barna|llengua=castellà}}
* [[1966]] - {{ref-llibre|títol=Consideraciones sobre uno de los componentes del teatro integral: El arte del agua-luz y lo romántico|url=http://books.google.com/books?id=9ZqMQQAACAAJ|any=1965|editorial=Real Academia de Ciencias y Artes de Barcelona|llengua=castellà}}, amb [[Bonaventura Bassegoda i Musté|Bassegoda Musté, Bonaventura]] 
* [[1973]] - {{ref-llibre|títol=Viajes interplanetarios y algo más|url=http://books.google.com/books?id=-LF7GQAACAAJ|any=1973|editorial=Ediciones Unidas|llengua=castellà|isbn=978-84-7168-007-5}}
* [[1973]] - {{ref-llibre|títol=Hechos, ideas y proyectos|url=http://books.google.com/books?id=egTMAAAACAAJ|any=1973|editorial=Ediciones Unidas|llengua=castellà|isbn=978-84-7168-008-2}}
* [[1975]] - {{ref-llibre|títol=La extraordinaria aventura|url=http://books.google.com/books?id=nhUYAAAACAAJ|any=1974|editorial=Ediciones Unidas|llengua=castellà|isbn=978-84-7168-010-5}}
* [[1975]] - {{ref-llibre|títol=La gran revolución|url=http://books.google.com/books?id=3L4eAAAAMAAJ|any=1975|editorial=Ediciones Marte|llengua=castellà|isbn=978-84-7249-171-7}}
* [[1976]] - {{ref-llibre|títol=El día 41|url=http://books.google.com/books?id=NJQKAQAAMAAJ|any=1976|editorial=Marte|llengua=castellà}}
* [[1978]] - {{ref-llibre|títol=La Fuente|url=http://books.google.com/books?id=UVSIAAAACAAJ|data= 1978|editorial=Marte|llengua=castellà|isbn=978-84-7249-178-6}}{{sfn|Buigas Sans |1978}}

== Fons personal ==
Part del seu fons personal es conserva a l'[[Arxiu Fotogràfic de Barcelona]]. El fons aplega documentació generada i reunida per Carles Buïgas. D'una banda, fotografies de caràcter personal, com retrats d'ell en diferents edats, de familiars i persones del seu entorn que mostren un ambient
íntim i proper a Buïgas. De l'altra, documentació reunida fruit de l'activitat professional que va desenvolupar com a enginyer. Formen part del fons, doncs, fotografies de projectes, alguns signats pel seu pare, de fonts, d'edificis civils, religiosos i monumentals. També es troben unes fotografies de la plaça Buïgas a Cerdanyola del Vallès que aquesta població va construir en honor a l'enginyer.ref name=AFB2007/

==Referències==
{{Referències|2}}

== Bibliografia ==
{{Commonscat}}

*{{ref-llibre |cognom=Buigas Sans |nom=Carlos |títol=La fuente |editorial=Marte |lloc=Barcelona |data=1978 |isbn=84-7249-178-1|ref=harv }}
*{{ref-llibre |cognom=Romero|nom=J. M. |títol=Carles Buïgas, el mag de l'aigua i de la llum |editorial=Ajuntament de Cerdanyola |lloc=Cerdanyola |data=1999 |isbn= }}
*{{ref-llibre |cognom=Silva|nom=Maria Paz |títol=22 anys amb Buigas |editorial=Nou Art Thor |lloc=Barcelona |data=1981 |isbn=84-7327-045-2|ref=harv }}
*{{ref-llibre |cognom=Tatjer|nom=Joan |títol=L'enginy de Carles Buigas (1898-1979) |editorial=Ajuntament de Barcelona - Agbar |lloc=Barcelona |data=1998 |isbn= |ref=harv}}
* [http://www.bcn.cat/buigas/lli.htm Edició electrònica del llibre-catàleg commemoratiu, L'ENGINY DE CARLES BUIGAS (1898-1979)], [[Ajuntament de Barcelona]]. 
** Capítol 6: Imatges de l'Exposició. Àmbit IV: [www.bcn.cat/buigas/pdf/amb4.pdf Carles Buigas i els seus projectes i obres], [[Ajuntament de Barcelona]].

== Enllaços externs ==
* [http://www.bcn.cat/buigas/lli.htm Edició electrònica del llibre-catàleg commemoratiu, L'ENGINY DE CARLES BUIGAS (1898-1979)], [[Ajuntament de Barcelona]].
** Capítol 3: [http://www.bcn.cat/buigas/pdf/fontmagica.pdf La Font Màgica] 
** Capítol 6: Imatges de l'Exposició. Àmbit IV: [http://www.bcn.cat/buigas/pdf/amb4.pdf Carles Buigas i els seus projectes i obres], [[Ajuntament de Barcelona]].
** etc.

{{Autoritat}}
{{ORDENA:Buigas, Carles}}

[[Categoria:Enginyers barcelonins]]
[[Categoria:Escriptors barcelonins contemporanis en castellà]]
[[Categoria:Membres de la Reial Acadèmia de Ciències i Arts de Barcelona]]
[[Categoria:Cerdanyolencs]]
[[Categoria:Alumnes de l'ETSEIB]]</text>
      <sha1>l7580m04vqyt5kvbbtctkpib0qnfvdf</sha1>
      <model>wikitext</model>
      <format>text/x-wiki</format>
    </revision>
  </page>